_fundamend_version.py
fundamend/__init__.py
fundamend/__main__.py
fundamend/py.typed
fundamend/sanitize.py
fundamend/utils.py
fundamend/commands/__init__.py
fundamend/commands/app.py
fundamend/commands/xml2json.py
fundamend/models/__init__.py
fundamend/models/anwendungshandbuch.py
fundamend/models/base.py
fundamend/models/kommunikationsrichtung.py
fundamend/models/messageimplementationguide.py
fundamend/reader/__init__.py
fundamend/reader/ahbreader.py
fundamend/reader/element_distinction.py
fundamend/reader/migreader.py
fundamend/sqlmodels/__init__.py
fundamend/sqlmodels/ahb_diff_view.py
fundamend/sqlmodels/ahbtabellen_view.py
fundamend/sqlmodels/ahbview.py
fundamend/sqlmodels/anwendungshandbuch.py
fundamend/sqlmodels/create_ahb_diff_view.sql
fundamend/sqlmodels/create_ahbtabellen_view.sql
fundamend/sqlmodels/expression_view.py
fundamend/sqlmodels/internals.py
fundamend/sqlmodels/materialize_ahb_view.sql
fundamend/sqlmodels/messageimplementationguide.py
fundamend-0.33.0.dist-info/METADATA
fundamend-0.33.0.dist-info/WHEEL
fundamend-0.33.0.dist-info/entry_points.txt
fundamend-0.33.0.dist-info/licenses/LICENSE
fundamend-0.33.0.dist-info/RECORD
