Metadata-Version: 2.4
Name: fundamend
Version: 0.33.0
Summary: XML basierte Formate und DatemModelle für die Energiewirtschaft in Deutschland
Project-URL: Changelog, https://github.com/Hochfrequenz/xml-fundamend-python/releases
Project-URL: Homepage, https://github.com/Hochfrequenz/xml-fundamend-python
Author-email: Hochfrequenz Unternehmensberatung GmbH <info+github@hochfrequenz.de>
License: MIT
License-File: LICENSE
Keywords: AHB,BDEW,MIG,Marktkommunikation,XML
Classifier: Development Status :: 4 - Beta
Classifier: Environment :: Console
Classifier: Intended Audience :: Developers
Classifier: License :: OSI Approved :: MIT License
Classifier: Operating System :: OS Independent
Classifier: Programming Language :: Python
Classifier: Programming Language :: Python :: 3 :: Only
Classifier: Programming Language :: Python :: 3.11
Classifier: Programming Language :: Python :: 3.12
Classifier: Programming Language :: Python :: 3.13
Classifier: Programming Language :: Python :: 3.14
Requires-Python: >=3.11
Requires-Dist: efoli>=2.1.0
Requires-Dist: pydantic>=2
Provides-Extra: ahbicht
Requires-Dist: ahbicht<2,>=1.0.0; extra == 'ahbicht'
Provides-Extra: cli
Requires-Dist: typer; extra == 'cli'
Provides-Extra: coverage
Requires-Dist: coverage==7.13.1; extra == 'coverage'
Provides-Extra: formatting
Requires-Dist: black==25.12.0; extra == 'formatting'
Requires-Dist: isort==7.0.0; extra == 'formatting'
Provides-Extra: linting
Requires-Dist: pylint==4.0.4; extra == 'linting'
Provides-Extra: spellcheck
Requires-Dist: codespell==2.4.1; extra == 'spellcheck'
Provides-Extra: sqlmodels
Requires-Dist: sqlalchemy[mypy]>=2.0.37; extra == 'sqlmodels'
Requires-Dist: sqlmodel>=0.0.22; extra == 'sqlmodels'
Provides-Extra: test-packaging
Requires-Dist: build==1.3.0; extra == 'test-packaging'
Requires-Dist: twine==6.2.0; extra == 'test-packaging'
Provides-Extra: tests
Requires-Dist: pytest==9.0.2; extra == 'tests'
Requires-Dist: syrupy==5.0.0; extra == 'tests'
Provides-Extra: type-check
Requires-Dist: mypy==1.19.1; extra == 'type-check'
